{
  "words": [
    "INVOICE",
    "INV-425700",
    "2025-06-18",
    "Maxwell-Marks",
    "Premium LEASE OR RENTAL OF EQUIPMENT- FIRE FIGHTING/RESCUE/SAFETY EQ",
    "7",
    "$374.45",
    "$2621.15",
    "Industrial INTERNATIONAL AFFAIRS R&D SERVICES Assembly",
    "9",
    "$129.86",
    "$1168.74",
    "MINERAL CONSTRUCTION MATERIALS, BULK Kit",
    "3",
    "$298.77",
    "$896.31",
    "$4686.20",
    "$374.90",
    "$5061.10"
  ],
  "boxes": [
    [
      325,
      50,
      424,
      67
    ],
    [
      50,
      107,
      108,
      117
    ],
    [
      375,
      107,
      431,
      117
    ],
    [
      50,
      157,
      124,
      167
    ],
    [
      55,
      222,
      320,
      233
    ],
    [
      452,
      222,
      458,
      232
    ],
    [
      556,
      222,
      596,
      233
    ],
    [
      647,
      222,
      693,
      233
    ],
    [
      55,
      267,
      373,
      279
    ],
    [
      452,
      267,
      458,
      277
    ],
    [
      556,
      267,
      596,
      278
    ],
    [
      648,
      267,
      693,
      278
    ],
    [
      55,
      292,
      311,
      304
    ],
    [
      452,
      292,
      458,
      302
    ],
    [
      556,
      292,
      596,
      303
    ],
    [
      653,
      292,
      693,
      303
    ],
    [
      654,
      347,
      700,
      358
    ],
    [
      660,
      372,
      700,
      383
    ],
    [
      641,
      410,
      700,
      424
    ]
  ],
  "ner_tags": [
    "B-HEADER",
    "B-INVOICE_NUM",
    "B-DATE",
    "B-VENDOR",
    "B-ITEM_DESC",
    "B-QTY",
    "B-PRICE",
    "B-TOTAL",
    "B-ITEM_DESC",
    "B-QTY",
    "B-PRICE",
    "B-TOTAL",
    "B-ITEM_DESC",
    "B-QTY",
    "B-PRICE",
    "B-TOTAL",
    "B-SUBTOTAL",
    "B-TAX",
    "B-TOTAL_AMT"
  ],
  "document_psc": "",
  "document_category": "Fire/Rescue/Safety/Environmental Protection Equipment",
  "document_portfolio": "Facility Related Services",
  "line_items_psc": [
    {
      "psc": "",
      "shortName": "LEASE OR RENTAL OF EQUIPMENT- FIRE FIGHTING/RESCUE/SAFETY EQUIPMENT; ENVIRON PROTECT EQUIPMENT/MATLS",
      "spendCategoryTitle": "Fire/Rescue/Safety/Environmental Protection Equipment",
      "portfolioGroup": "Facility Related Services",
      "description": "Premium LEASE OR RENTAL OF EQUIPMENT- FIRE FIGHTING/RESCUE/SAFETY EQ",
      "line_total": 2621.15
    },
    {
      "psc": "",
      "shortName": "INTERNATIONAL AFFAIRS R&D SERVICES; INTERNATIONAL AFFAIRS; BASIC RESEARCH",
      "spendCategoryTitle": "",
      "portfolioGroup": "Research and Development",
      "description": "Industrial INTERNATIONAL AFFAIRS R&D SERVICES Assembly",
      "line_total": 1168.74
    },
    {
      "psc": "",
      "shortName": "MINERAL CONSTRUCTION MATERIALS, BULK",
      "spendCategoryTitle": "Construction Related Materials",
      "portfolioGroup": "Facilities S&E",
      "description": "MINERAL CONSTRUCTION MATERIALS, BULK Kit",
      "line_total": 896.31
    }
  ],
  "psc_breakdown": {
    "Fire/Rescue/Safety/Environmental Protection Equipment": 2621.15,
    "": 1168.74,
    "Construction Related Materials": 896.31
  },
  "portfolio_breakdown": {
    "Facility Related Services": 2621.15,
    "Research and Development": 1168.74,
    "Facilities S&E": 896.31
  },
  "invoice_metadata": {
    "invoice_id": "INV-425700",
    "date": "2025-06-18",
    "vendor_name": "Maxwell-Marks",
    "total_amount": 5061.1
  }
}