{
  "words": [
    "INVOICE",
    "INV-543738",
    "2025-05-29",
    "Wright, Martinez and Gregory",
    "Premium TRANSPORTATION/TRAVEL/RELOCATION- TRANSPORTATION: RAIL CHART Kit",
    "4",
    "$76.65",
    "$306.60",
    "Professional LUGS, TERMINALS, AND TERMINAL STRIPS Kit",
    "1",
    "$339.32",
    "$339.32",
    "Standard COMBAT, ASSAULT, AND TACTICAL VEHICLES, WHEELED",
    "11",
    "$711.86",
    "$7830.46",
    "Premium CUTTING Package",
    "11",
    "$313.91",
    "$3453.01",
    "Industrial HOSPITAL FURNITURE, EQUIPMENT, UTENSILS, AND SUPPLIES Assembly",
    "1",
    "$111.94",
    "$111.94",
    "$12041.33",
    "$1505.17",
    "$13546.50"
  ],
  "boxes": [
    [
      325,
      50,
      424,
      67
    ],
    [
      50,
      107,
      108,
      117
    ],
    [
      375,
      107,
      431,
      117
    ],
    [
      50,
      157,
      195,
      169
    ],
    [
      55,
      222,
      324,
      232
    ],
    [
      452,
      222,
      458,
      232
    ],
    [
      562,
      222,
      596,
      233
    ],
    [
      653,
      222,
      693,
      233
    ],
    [
      55,
      267,
      363,
      279
    ],
    [
      452,
      267,
      458,
      277
    ],
    [
      556,
      267,
      596,
      278
    ],
    [
      653,
      267,
      693,
      278
    ],
    [
      55,
      292,
      346,
      304
    ],
    [
      450,
      292,
      461,
      302
    ],
    [
      557,
      292,
      596,
      303
    ],
    [
      647,
      292,
      693,
      303
    ],
    [
      55,
      337,
      197,
      349
    ],
    [
      450,
      337,
      461,
      347
    ],
    [
      556,
      337,
      596,
      348
    ],
    [
      647,
      337,
      693,
      348
    ],
    [
      55,
      362,
      382,
      374
    ],
    [
      452,
      362,
      458,
      372
    ],
    [
      558,
      362,
      596,
      373
    ],
    [
      655,
      362,
      693,
      373
    ],
    [
      648,
      437,
      700,
      448
    ],
    [
      654,
      462,
      700,
      473
    ],
    [
      634,
      500,
      700,
      514
    ]
  ],
  "ner_tags": [
    "B-HEADER",
    "B-INVOICE_NUM",
    "B-DATE",
    "B-VENDOR",
    "B-ITEM_DESC",
    "B-QTY",
    "B-PRICE",
    "B-TOTAL",
    "B-ITEM_DESC",
    "B-QTY",
    "B-PRICE",
    "B-TOTAL",
    "B-ITEM_DESC",
    "B-QTY",
    "B-PRICE",
    "B-TOTAL",
    "B-ITEM_DESC",
    "B-QTY",
    "B-PRICE",
    "B-TOTAL",
    "B-ITEM_DESC",
    "B-QTY",
    "B-PRICE",
    "B-TOTAL",
    "B-SUBTOTAL",
    "B-TAX",
    "B-TOTAL_AMT"
  ],
  "document_psc": "",
  "document_category": "Land Combat Vehicles",
  "document_portfolio": "Aircraft, Ships/Submarines & Land Vehicles",
  "line_items_psc": [
    {
      "psc": "",
      "shortName": "TRANSPORTATION/TRAVEL/RELOCATION- TRANSPORTATION: RAIL CHARTER",
      "spendCategoryTitle": "Transportation of Things",
      "portfolioGroup": "Transportation Services",
      "description": "Premium TRANSPORTATION/TRAVEL/RELOCATION- TRANSPORTATION: RAIL CHART Kit",
      "line_total": 306.6
    },
    {
      "psc": "",
      "shortName": "LUGS, TERMINALS, AND TERMINAL STRIPS",
      "spendCategoryTitle": "Electrical & Electronics Equipment",
      "portfolioGroup": "Electronic & Communication Equipment",
      "description": "Professional LUGS, TERMINALS, AND TERMINAL STRIPS Kit",
      "line_total": 339.32
    },
    {
      "psc": "",
      "shortName": "COMBAT, ASSAULT, AND TACTICAL VEHICLES, WHEELED",
      "spendCategoryTitle": "Land Combat Vehicles",
      "portfolioGroup": "Aircraft, Ships/Submarines & Land Vehicles",
      "description": "Standard COMBAT, ASSAULT, AND TACTICAL VEHICLES, WHEELED",
      "line_total": 7830.46
    },
    {
      "psc": "",
      "shortName": "CUTTING AND FORMING TOOLS FOR SECONDARY METALWORKING MACHINERY",
      "spendCategoryTitle": "Machinery & Components",
      "portfolioGroup": "Facilities S&E",
      "description": "Premium CUTTING Package",
      "line_total": 3453.01
    },
    {
      "psc": "",
      "shortName": "HOSPITAL FURNITURE, EQUIPMENT, UTENSILS, AND SUPPLIES",
      "spendCategoryTitle": "Medical Equipment and Accessories and Supplies",
      "portfolioGroup": "Clothing, Textiles & Subsistence S&E",
      "description": "Industrial HOSPITAL FURNITURE, EQUIPMENT, UTENSILS, AND SUPPLIES Assembly",
      "line_total": 111.94
    }
  ],
  "psc_breakdown": {
    "Transportation of Things": 306.6,
    "Electrical & Electronics Equipment": 339.32,
    "Land Combat Vehicles": 7830.46,
    "Machinery & Components": 3453.01,
    "Medical Equipment and Accessories and Supplies": 111.94
  },
  "portfolio_breakdown": {
    "Transportation Services": 306.6,
    "Electronic & Communication Equipment": 339.32,
    "Aircraft, Ships/Submarines & Land Vehicles": 7830.46,
    "Facilities S&E": 3453.01,
    "Clothing, Textiles & Subsistence S&E": 111.94
  },
  "invoice_metadata": {
    "invoice_id": "INV-543738",
    "date": "2025-05-29",
    "vendor_name": "Wright, Martinez and Gregory",
    "total_amount": 13546.5
  }
}